riff_api/__init__.py
riff_api/api.py
riff_api/types.py
riff_api-0.4.2.dist-info/licenses/LICENSE
riff_api-0.4.2.dist-info/METADATA
riff_api-0.4.2.dist-info/WHEEL
riff_api-0.4.2.dist-info/top_level.txt
riff_api-0.4.2.dist-info/RECORD
