Metadata-Version: 2.4
Name: riff_api
Version: 0.4.2
Summary: Riffusion API
Author-email: Hayk Martiros <hayk@riffusion.com>, Naveen Iyer <naveen@riffusion.com>
Project-URL: Homepage, https://github.com/corpusant-ai/riff-api/
Project-URL: Issues, https://github.com/corpusant-ai/riff-api/issues
Classifier: Programming Language :: Python :: 3
Classifier: License :: OSI Approved :: Apache Software License
Classifier: Operating System :: OS Independent
Requires-Python: >=3.8
License-File: LICENSE
Requires-Dist: pydantic>=2.0.0
Requires-Dist: requests>=2.25.1
Requires-Dist: types-requests>=2.31.0
Dynamic: license-file
